uactor.py
uactor-0.1.1.dist-info/LICENSE
uactor-0.1.1.dist-info/METADATA
uactor-0.1.1.dist-info/WHEEL
uactor-0.1.1.dist-info/top_level.txt
uactor-0.1.1.dist-info/zip-safe
uactor-0.1.1.dist-info/RECORD
