Metadata-Version: 2.1
Name: uactor
Version: 0.1.1
Summary: uActor: Process Actor Model
Home-page: https://gitlab.com/ergoithz/uactor
Author: Felipe A Hernandez
Author-email: ergoithz@gmail.com
License: MIT
Keywords: actor,multiprocessing
Platform: any
Classifier: License :: OSI Approved :: MIT License
Classifier: Development Status :: 4 - Beta
Classifier: Programming Language :: Python :: Implementation :: PyPy
Classifier: Programming Language :: Python :: Implementation :: CPython
Classifier: Operating System :: OS Independent
Classifier: Programming Language :: Python :: 3
Classifier: Programming Language :: Python :: 3.6
Classifier: Programming Language :: Python :: 3.7
Classifier: Programming Language :: Python :: 3.8
Classifier: Programming Language :: Python :: 3.9
Classifier: Topic :: Software Development :: Libraries
Classifier: Topic :: System :: Distributed Computing
Classifier: Topic :: System :: Hardware :: Symmetric Multi-processing
Requires-Python: >=3.6.0
Provides-Extra: codestyle
Requires-Dist: flake8 ; extra == 'codestyle'
Requires-Dist: flake8-blind-except ; extra == 'codestyle'
Requires-Dist: flake8-bugbear ; extra == 'codestyle'
Requires-Dist: flake8-builtins ; extra == 'codestyle'
Requires-Dist: flake8-commas ; extra == 'codestyle'
Requires-Dist: flake8-docstrings ; extra == 'codestyle'
Requires-Dist: flake8-import-order ; extra == 'codestyle'
Requires-Dist: flake8-logging-format ; extra == 'codestyle'
Requires-Dist: flake8-rst-docstrings ; extra == 'codestyle'
Provides-Extra: coverage
Requires-Dist: coverage ; extra == 'coverage'
Provides-Extra: docs
Requires-Dist: recommonmark ; extra == 'docs'
Requires-Dist: sphinx ; extra == 'docs'
Provides-Extra: release
Requires-Dist: wheel ; extra == 'release'
Requires-Dist: twine ; extra == 'release'
Provides-Extra: tests
Requires-Dist: coverage ; extra == 'tests'
